eip712_structs/__init__.py
eip712_structs/domain_separator.py
eip712_structs/struct.py
eip712_structs/types.py
eip712_structs-0.1.6.dist-info/LICENSE
eip712_structs-0.1.6.dist-info/METADATA
eip712_structs-0.1.6.dist-info/WHEEL
eip712_structs-0.1.6.dist-info/top_level.txt
eip712_structs-0.1.6.dist-info/RECORD
