Metadata-Version: 2.1
Name: eip712-structs
Version: 0.1.6
Summary: UNKNOWN
Home-page: https://github.com/ajrgrubbs/py-eip712-structs
License: MIT
Keywords: ethereum eip712
Platform: UNKNOWN
Requires-Dist: eth-utils (==1.4.1)
Requires-Dist: pysha3 (==1.0.2)
